pythiarg/__init__.py
pythiarg/__main__.py
pythiarg/util.py
pythiarg/tables/__init__.py
pythiarg/tables/badevank.py
pythiarg/tables/evank.py
pythiarg/tables/pyt.py
pythiarg/tables/template.py
pythiarg-0.5.1.dist-info/LICENSE
pythiarg-0.5.1.dist-info/METADATA
pythiarg-0.5.1.dist-info/WHEEL
pythiarg-0.5.1.dist-info/entry_points.txt
pythiarg-0.5.1.dist-info/top_level.txt
pythiarg-0.5.1.dist-info/RECORD
