Metadata-Version: 2.1
Name: pythiarg
Version: 0.5.1
Summary: Random generator for rpgs and the sort.
Author-email: Todd Sonjiku <dev.50nj1ku@erine.email>
Maintainer-email: Todd Sonjiku <dev.50nj1ku@erine.email>
License: MIT License
Project-URL: Homepage, https://github.com/sonjiku/pythiarg
Project-URL: Documentation, https://github.com/sonjiku/pythiarg/wiki
Project-URL: Source, https://github.com/sonjiku/pythiarg.git
Project-URL: Issues, https://github.com/sonjiku/pythiarg/issues
Project-URL: Changelog, https://github.com/sonjiku/pythiarg/blob/main/CHANGELOG.md
Keywords: pythia,oracle,dnd,trpg,ttrpg,generator,random generator
Classifier: Development Status :: 4 - Beta
Classifier: Environment :: Console
Classifier: Intended Audience :: Developers
Classifier: Intended Audience :: Education
Classifier: Intended Audience :: End Users/Desktop
Classifier: Intended Audience :: Other Audience
Classifier: License :: OSI Approved :: MIT License
Classifier: Programming Language :: Python :: 3
Classifier: Programming Language :: Python :: 3.12
Classifier: Natural Language :: English
Classifier: Topic :: Games/Entertainment :: Board Games
Classifier: Topic :: Games/Entertainment :: Role-Playing
Classifier: Topic :: Utilities
Classifier: Typing :: Typed
Requires-Python: <3.13,>=3.12
License-File: LICENSE
